mpx/__init__.py
mpx/clients.py
mpx/exceptions.py
mpx-0.1.dist-info/DESCRIPTION.rst
mpx-0.1.dist-info/METADATA
mpx-0.1.dist-info/metadata.json
mpx-0.1.dist-info/RECORD
mpx-0.1.dist-info/top_level.txt
mpx-0.1.dist-info/WHEEL
