Metadata-Version: 2.0
Name: mpx
Version: 0.1
Summary: Python client for thePlatform MPX API.
Home-page: https://github.com/khilnani/mpx
Author: khilnani
Author-email: nik@khilnani.org
License: MIT
Keywords: mpx,thePlatform,pdk
Platform: UNKNOWN
Classifier: Development Status :: 3 - Alpha
Classifier: Environment :: Console
Classifier: Environment :: Console
Classifier: Intended Audience :: Developers
Classifier: Intended Audience :: System Administrators
Classifier: License :: OSI Approved :: MIT License
Classifier: Operating System :: MacOS :: MacOS X
Classifier: Operating System :: Unix
Classifier: Operating System :: POSIX
Classifier: Programming Language :: Python
Classifier: Programming Language :: Python :: 2.7
Classifier: Topic :: Software Development
Classifier: Topic :: Software Development :: Libraries
Classifier: Topic :: Software Development :: Libraries :: Python Modules
Classifier: Topic :: Multimedia :: Video
Requires-Dist: requests
Requires-Dist: texttable
